datalab_app/__init__.py
datalab_app-0.0.1.dev0.dist-info/licenses/LICENSE
datalab_app-0.0.1.dev0.dist-info/METADATA
datalab_app-0.0.1.dev0.dist-info/WHEEL
datalab_app-0.0.1.dev0.dist-info/entry_points.txt
datalab_app-0.0.1.dev0.dist-info/top_level.txt
datalab_app-0.0.1.dev0.dist-info/RECORD
